haystack_integrations/components/generators/py.typed
haystack_integrations/components/generators/amazon_sagemaker/__init__.py
haystack_integrations/components/generators/amazon_sagemaker/errors.py
haystack_integrations/components/generators/amazon_sagemaker/sagemaker.py
amazon_sagemaker_haystack-1.0.0.dist-info/METADATA
amazon_sagemaker_haystack-1.0.0.dist-info/WHEEL
amazon_sagemaker_haystack-1.0.0.dist-info/licenses/LICENSE.txt
amazon_sagemaker_haystack-1.0.0.dist-info/RECORD
