Metadata-Version: 2.4
Name: amazon-sagemaker-haystack
Version: 1.0.0
Summary: An integration of Amazon Sagemaker as an SagemakerGenerator component.
Project-URL: Documentation, https://github.com/deepset-ai/haystack-core-integrations/tree/main/integrations/amazon_sagemaker_haystack#readme
Project-URL: Issues, https://github.com/deepset-ai/haystack-core-integrations/tree/main/integrations/amazon_sagemaker_haystack/issues
Project-URL: Source, https://github.com/deepset-ai/haystack-core-integrations/tree/main/integrations/amazon_sagemaker_haystack
Author-email: deepset GmbH <info@deepset.ai>
License-Expression: Apache-2.0
License-File: LICENSE.txt
Classifier: Development Status :: 4 - Beta
Classifier: License :: OSI Approved :: Apache Software License
Classifier: Programming Language :: Python
Classifier: Programming Language :: Python :: 3.10
Classifier: Programming Language :: Python :: 3.11
Classifier: Programming Language :: Python :: 3.12
Classifier: Programming Language :: Python :: 3.13
Classifier: Programming Language :: Python :: Implementation :: CPython
Classifier: Programming Language :: Python :: Implementation :: PyPy
Requires-Python: >=3.10
Requires-Dist: boto3>=1.28.57
Requires-Dist: haystack-ai>=2.22.0
